README.md
setup.py
ZhihuTool/__init__.py
ZhihuTool/login.py
ZhihuTool/upload.py
ZhihuTool/utils.py
ZhihuTool.egg-info/PKG-INFO
ZhihuTool.egg-info/SOURCES.txt
ZhihuTool.egg-info/dependency_links.txt
ZhihuTool.egg-info/requires.txt
ZhihuTool.egg-info/top_level.txt
zhihutool.egg-info/PKG-INFO
zhihutool.egg-info/SOURCES.txt
zhihutool.egg-info/dependency_links.txt
zhihutool.egg-info/requires.txt
zhihutool.egg-info/top_level.txt